README.md
setup.cfg
setup.py
web_crawler/__init__.py
web_crawler/aggregators.py
web_crawler/config.py
web_crawler/launch.py
web_crawler/redis_pool.py
web_crawler/tasks.py
web_crawler.egg-info/PKG-INFO
web_crawler.egg-info/SOURCES.txt
web_crawler.egg-info/dependency_links.txt
web_crawler.egg-info/requires.txt
web_crawler.egg-info/top_level.txt