Metadata-Version: 1.0
Name: web-crawler
Version: 0.0.4
Summary: Web crawler
Home-page: https://github.com/ricbartm/web-crawler
Author: Ricardo Bartolome
Author-email: UNKNOWN
License: UNKNOWN
Platform: UNKNOWN
